fastoad/__init__.py
fastoad/_utils/__init__.py
fastoad/_utils/arrays.py
fastoad/_utils/dicts.py
fastoad/_utils/files.py
fastoad/_utils/pandas.py
fastoad/_utils/resource_management/__init__.py
fastoad/_utils/resource_management/contents.py
fastoad/_utils/resource_management/copy.py
fastoad/_utils/sellar/__init__.py
fastoad/_utils/sellar/disc1.py
fastoad/_utils/sellar/disc2.py
fastoad/_utils/sellar/function_f.py
fastoad/_utils/sellar/functions_g.py
fastoad/_utils/sellar/sellar_base.py
fastoad/_utils/strings.py
fastoad/api.py
fastoad/cmd/__init__.py
fastoad/cmd/api.py
fastoad/cmd/calc_runner.py
fastoad/cmd/cli.py
fastoad/cmd/cli_utils.py
fastoad/cmd/exceptions.py
fastoad/cmd/resources/__init__.py
fastoad/cmd/resources/fastoad.yml
fastoad/configurations/__init__.py
fastoad/constants.py
fastoad/exceptions.py
fastoad/gui/__init__.py
fastoad/gui/analysis_and_plots.py
fastoad/gui/exceptions.py
fastoad/gui/mission_viewer.py
fastoad/gui/optimization_viewer.py
fastoad/gui/variable_viewer.py
fastoad/io/__init__.py
fastoad/io/configuration/__init__.py
fastoad/io/configuration/configuration.py
fastoad/io/configuration/exceptions.py
fastoad/io/configuration/resources/__init__.py
fastoad/io/configuration/resources/configuration.json
fastoad/io/formatter.py
fastoad/io/variable_io.py
fastoad/io/xml/__init__.py
fastoad/io/xml/constants.py
fastoad/io/xml/exceptions.py
fastoad/io/xml/resources/__init__.py
fastoad/io/xml/resources/legacy1.txt
fastoad/io/xml/resources/remove_duplicate_variables.py
fastoad/io/xml/translator.py
fastoad/io/xml/variable_io_base.py
fastoad/io/xml/variable_io_legacy.py
fastoad/io/xml/variable_io_standard.py
fastoad/model_base/__init__.py
fastoad/model_base/atmosphere.py
fastoad/model_base/datacls.py
fastoad/model_base/flight_point.py
fastoad/model_base/openmdao/__init__.py
fastoad/model_base/openmdao/group.py
fastoad/model_base/propulsion.py
fastoad/models/__init__.py
fastoad/models/performances/__init__.py
fastoad/models/performances/mission/__init__.py
fast_oad_core-1.8.4.dist-info/AUTHORS.rst
fast_oad_core-1.8.4.dist-info/LICENSE.txt
fast_oad_core-1.8.4.dist-info/METADATA
fast_oad_core-1.8.4.dist-info/WHEEL
fast_oad_core-1.8.4.dist-info/entry_points.txt
fast_oad_core-1.8.4.dist-info/RECORD
