Metadata-Version: 2.1
Name: FAST-OAD-core
Version: 1.8.4
Summary: FAST-OAD is a framework for performing rapid Overall Aircraft Design
Home-page: https://github.com/fast-aircraft-design/FAST-OAD
License: GPL-3.0-only
Keywords: aircraft,design,multi-disciplinary
Author: Christophe DAVID
Author-email: christophe.david@onera.fr
Requires-Python: >=3.9,<3.13
Classifier: Development Status :: 5 - Production/Stable
Classifier: Environment :: Console
Classifier: Intended Audience :: Education
Classifier: Intended Audience :: Science/Research
Classifier: License :: OSI Approved :: GNU General Public License v3 (GPLv3)
Classifier: Natural Language :: English
Classifier: Operating System :: MacOS
Classifier: Operating System :: Microsoft :: Windows
Classifier: Operating System :: POSIX :: Linux
Classifier: Programming Language :: Python :: 3
Classifier: Programming Language :: Python :: 3.9
Classifier: Programming Language :: Python :: 3.10
Classifier: Programming Language :: Python :: 3.11
Classifier: Programming Language :: Python :: 3.12
Classifier: Topic :: Scientific/Engineering :: Physics
Provides-Extra: mpi
Provides-Extra: mpi4py
Requires-Dist: Deprecated (>=1.2.13,<2.0.0)
Requires-Dist: aenum (>=3.1.0,<4.0.0)
Requires-Dist: anywidget (>=0.9.18,<0.10.0)
Requires-Dist: click (>=8.0.3,<9.0.0)
Requires-Dist: ensure (>=1.0.0,<2.0.0) ; python_version < "3.12"
Requires-Dist: ensure (>=1.0.4,<2.0.0) ; python_version >= "3.12" and python_version < "4.0"
Requires-Dist: importlib-metadata (>=4.2,<5.0) ; python_version < "3.10"
Requires-Dist: ipopo (>=1.0.0,<2.0.0) ; python_version < "3.10"
Requires-Dist: ipopo (>=3.0.0,<4.0.0) ; python_version >= "3.10" and python_version < "4.0"
Requires-Dist: ipysheet (>=0.5.0,<1)
Requires-Dist: ipywidgets (>=7.7.0,<9)
Requires-Dist: jsonschema (>=3.2.0,<5)
Requires-Dist: jupyterlab (>=3.4.7,<4.0.0) ; python_version < "3.12"
Requires-Dist: jupyterlab (>=4.2,<5.0) ; python_version >= "3.12" and python_version < "4.0"
Requires-Dist: lxml (>=4.6.5,<6) ; python_version < "3.11"
Requires-Dist: lxml (>=4.9.3,<6) ; python_version >= "3.11" and python_version < "4.0"
Requires-Dist: mpi4py (>=4.0.2,<5.0.0) ; extra == "mpi" or extra == "mpi4py"
Requires-Dist: numpy (>=1.23.2,<3)
Requires-Dist: openmdao (>3.27,<3.39)
Requires-Dist: pandas (>=1.3.4,<3) ; python_version < "3.11"
Requires-Dist: pandas (>=1.5.3,<3) ; python_version >= "3.11" and python_version < "3.12"
Requires-Dist: pandas (>=2.1.1,<3.0.0) ; python_version >= "3.12" and python_version < "4.0"
Requires-Dist: plotly (>=6.2.0,<7.0.0)
Requires-Dist: pyDOE3 (>=1.0.0,<2.0.0)
Requires-Dist: rich (>=14.0.0,<15.0.0)
Requires-Dist: ruamel.yaml (>=0.15.78,<0.18)
Requires-Dist: scipy (>=1.11.2,<2.0.0)
Requires-Dist: stdatm (>=0.4.2)
Requires-Dist: tabulate (>=0.8.9,<1)
Requires-Dist: tomlkit (>=0.5.3,<1)
Requires-Dist: wop (>=2.2.0,<3.0.0)
